flatspin/__init__.py
flatspin/_version.py
flatspin/astroid.py
flatspin/astroids.csv
flatspin/cmdline.py
flatspin/data.py
flatspin/encoder.py
flatspin/flatspin_cl_kernels.c
flatspin/flatspin_cuda_kernels.cu
flatspin/grid.py
flatspin/model.py
flatspin/plotting.py
flatspin/runner.py
flatspin/sweep.py
flatspin/utils.py
flatspin/vertices.py
flatspin/tools/__init__.py
flatspin/tools/convert.py
flatspin/tools/fsck.py
flatspin/tools/inspect.py
flatspin/tools/plot.py
flatspin/tools/plot_table.py
flatspin/tools/progress.py
flatspin/tools/run.py
flatspin/tools/run_sweep.py
flatspin/tools/stats.py
flatspin/tools/vectors.py
flatspin/tools/vertices.py
flatspin-2.5.1.dist-info/AUTHORS
flatspin-2.5.1.dist-info/LICENSE
flatspin-2.5.1.dist-info/METADATA
flatspin-2.5.1.dist-info/WHEEL
flatspin-2.5.1.dist-info/entry_points.txt
flatspin-2.5.1.dist-info/top_level.txt
flatspin-2.5.1.dist-info/RECORD
