Metadata-Version: 2.2
Name: flatspin
Version: 2.5.1
Summary: Artificial Spin Ice simulator
Home-page: https://flatspin.gitlab.io/
Author: Johannes H. Jensen
Author-email: johannes.jensen@ntnu.no
License: GPLv3
Project-URL: Source, https://gitlab.com/flatspin/flatspin
Project-URL: Documentation, https://flatspin.gitlab.io
Project-URL: Tracker, https://gitlab.com/flatspin/flatspin/issues
Classifier: Programming Language :: Python :: 3
Classifier: License :: OSI Approved :: GNU General Public License v3 (GPLv3)
Classifier: Operating System :: OS Independent
Requires-Python: >=3.7
License-File: LICENSE
License-File: AUTHORS
Requires-Dist: numpy>=1.17
Requires-Dist: scipy
Requires-Dist: pandas>=0.23.0
Requires-Dist: tables
Requires-Dist: matplotlib>=3.5.0
Requires-Dist: pyopencl
Requires-Dist: siphash24
Requires-Dist: pillow>=9.1.0
Requires-Dist: joblib
Requires-Dist: numba
Requires-Dist: tqdm
Requires-Dist: scikit-image
Requires-Dist: setuptools_scm
Requires-Dist: shapely
Provides-Extra: cuda
Requires-Dist: pycuda; extra == "cuda"
Provides-Extra: test
Requires-Dist: pytest; extra == "test"
Requires-Dist: pytest-benchmark; extra == "test"
Requires-Dist: pycuda; extra == "test"
Provides-Extra: docs
Requires-Dist: ipython!=8.7.0; extra == "docs"
Requires-Dist: jupyter-book>=0.13.2; extra == "docs"
Requires-Dist: sphinxcontrib-autoprogram; extra == "docs"
Provides-Extra: dev
Requires-Dist: pytest; extra == "dev"
Requires-Dist: pytest-benchmark; extra == "dev"
Requires-Dist: jupyter-book>=0.13.2; extra == "dev"
Requires-Dist: sphinxcontrib-autoprogram; extra == "dev"
